stick/__init__.py
stick/commands.py
stick/j2.py
stick/project.py
stick/repository.py
stick/settings.py
stick/util.py
stick/templates/index.html.j2
stick/templates/release.html.j2
stick/templates/repository_index.html.j2
stick-0.5.4.dist-info/LICENSE
stick-0.5.4.dist-info/METADATA
stick-0.5.4.dist-info/WHEEL
stick-0.5.4.dist-info/entry_points.txt
stick-0.5.4.dist-info/top_level.txt
stick-0.5.4.dist-info/version.txt
stick-0.5.4.dist-info/version_full.txt
stick-0.5.4.dist-info/RECORD
